{"af":{"code":"ZA","name":"Південно-Африканська Республіка"},"ar":{"code":"EG","name":"Єгипет"},"az":{"code":"AZ","name":"Азербайджан"},"be":{"code":"BY","name":"Білорусь"},"bg":{"code":"BG","name":"Болгарія"},"bn":{"code":"BD","name":"Бангладеш"},"bs":{"code":"BA","name":"Боснія І Герцеговина"},"ca":{"code":"ES","name":"Іспанія"},"cs":{"code":"CZ","name":"Чехія"},"cy":{"code":"GB","name":"Велика Британія"},"da":{"code":"DK","name":"Данія"},"de":{"code":"DE","name":"Німеччина"},"de_CH":{"code":"CH","name":"Швейцарія"},"el":{"code":"GR","name":"Греція"},"en":{"code":"US","name":"Сполучені Штати"},"es":{"code":"ES","name":"Іспанія"},"et":{"code":"EE","name":"Естонія"},"eu":{"code":"ES","name":"Іспанія"},"fa":{"code":"IR","name":"Іран"},"fi":{"code":"FI","name":"Фінляндія"},"fil":{"code":"PH","name":"Філіппіни"},"fr":{"code":"FR","name":"Франція"},"gl":{"code":"ES","name":"Іспанія"},"gu":{"code":"IN","name":"Індія"},"he":{"code":"IL","name":"Ізраїль"},"hi":{"code":"IN","name":"Індія"},"hr":{"code":"HR","name":"Хорватія"},"hu":{"code":"HU","name":"Угорщина"},"hy":{"code":"AM","name":"Вірменія"},"id":{"code":"ID","name":"Індонезія"},"is":{"code":"IS","name":"Ісландія"},"it":{"code":"IT","name":"Італія"},"ja":{"code":"JP","name":"Японія"},"ka":{"code":"GE","name":"Грузія"},"kk":{"code":"KZ","name":"Казахстан"},"km":{"code":"KH","name":"Камбоджа"},"kn":{"code":"IN","name":"Індія"},"ko":{"code":"KR","name":"Південна Корея"},"lt":{"code":"LT","name":"Литва"},"lv":{"code":"LV","name":"Латвія"},"mk":{"code":"MK","name":"Північна Македонія"},"mn":{"code":"MN","name":"Монголія"},"mr":{"code":"IN","name":"Індія"},"ms":{"code":"MY","name":"Малайзія"},"nb":{"code":"NO","name":"Норвегія"},"ne":{"code":"NP","name":"Непал"},"nl":{"code":"NL","name":"Нідерланди"},"nn":{"code":"NO","name":"Норвегія"},"oc":{"code":"FR","name":"Франція"},"pl":{"code":"PL","name":"Польща"},"ps":{"code":"AF","name":"Афганістан"},"pt":{"code":"BR","name":"Бразилія"},"pt_BR":{"code":"BR","name":"Бразилія"},"ro":{"code":"RO","name":"Румунія"},"ru":{"code":"RU","name":"Росія"},"sc":{"code":"IT","name":"Італія"},"si":{"code":"LK","name":"Шрі-Ланка"},"sk":{"code":"SK","name":"Словаччина"},"sl":{"code":"SI","name":"Словенія"},"sq":{"code":"AL","name":"Албанія"},"sr_Cyrl":{"code":"RS","name":"Сербія"},"sr_Latn":{"code":"RS","name":"Сербія"},"sr_Latn_ME":{"code":"ME","name":"Чорногорія"},"sv":{"code":"SE","name":"Швеція"},"sw":{"code":"TZ","name":"Танзанія"},"tg":{"code":"TJ","name":"Таджикистан"},"th":{"code":"TH","name":"Таїланд"},"tk":{"code":"TM","name":"Туркменістан"},"tl":{"code":"PH","name":"Філіппіни"},"tr":{"code":"TR","name":"Туреччина"},"ug":{"code":"CN","name":"Китай"},"uk":{"code":"UA","name":"Україна"},"ur":{"code":"PK","name":"Пакистан"},"uz_Cyrl":{"code":"UZ","name":"Узбекистан"},"uz_Latn":{"code":"UZ","name":"Узбекистан"},"vi":{"code":"VN","name":"Вʼєтнам"},"zh_CN":{"code":"CN","name":"Китай"},"zh_HK":{"code":"HK","name":"Гонконг, Оар Китаю"},"zh_TW":{"code":"TW","name":"Тайвань"}}
